latex_generator_mr.py
latex_generator_mr-0.3.0.dist-info/METADATA
latex_generator_mr-0.3.0.dist-info/WHEEL
latex_generator_mr-0.3.0.dist-info/RECORD
