Metadata-Version: 2.1
Name: latex-generator-mr
Version: 0.3.0
Summary: Class for generating LaTeX code for tables and images.
Author: Mikhail-Repkin
Author-email: mikhail.repkin90@gmail.com
Requires-Python: >=3.11,<4.0
Classifier: Programming Language :: Python :: 3
Classifier: Programming Language :: Python :: 3.11
Classifier: Programming Language :: Python :: 3.12
